aiovemmio/__init__.py
aiovemmio/accelerometer.proto
aiovemmio/accelerometer_pb2.py
aiovemmio/accelerometer_pb2.pyi
aiovemmio/addon.proto
aiovemmio/addon_pb2.py
aiovemmio/addon_pb2.pyi
aiovemmio/admin.proto
aiovemmio/admin_pb2.py
aiovemmio/admin_pb2.pyi
aiovemmio/battery.proto
aiovemmio/battery_pb2.py
aiovemmio/battery_pb2.pyi
aiovemmio/ble.proto
aiovemmio/ble_pb2.py
aiovemmio/ble_pb2.pyi
aiovemmio/bsensor.proto
aiovemmio/bsensor_pb2.py
aiovemmio/bsensor_pb2.pyi
aiovemmio/carbon_dioxide.proto
aiovemmio/carbon_dioxide_pb2.py
aiovemmio/carbon_dioxide_pb2.pyi
aiovemmio/carbon_monoxide.proto
aiovemmio/carbon_monoxide_pb2.py
aiovemmio/carbon_monoxide_pb2.pyi
aiovemmio/color.proto
aiovemmio/color_pb2.py
aiovemmio/color_pb2.pyi
aiovemmio/configuration.proto
aiovemmio/configuration_pb2.py
aiovemmio/configuration_pb2.pyi
aiovemmio/const.py
aiovemmio/devices.proto
aiovemmio/devices_pb2.py
aiovemmio/devices_pb2.pyi
aiovemmio/door.proto
aiovemmio/door_pb2.py
aiovemmio/door_pb2.pyi
aiovemmio/doorbell.proto
aiovemmio/doorbell_pb2.py
aiovemmio/doorbell_pb2.pyi
aiovemmio/emergency.proto
aiovemmio/emergency_pb2.py
aiovemmio/emergency_pb2.pyi
aiovemmio/firmware.proto
aiovemmio/firmware_pb2.py
aiovemmio/firmware_pb2.pyi
aiovemmio/flood.proto
aiovemmio/flood_pb2.py
aiovemmio/flood_pb2.pyi
aiovemmio/gate.proto
aiovemmio/gate_pb2.py
aiovemmio/gate_pb2.pyi
aiovemmio/gateway.proto
aiovemmio/gateway_pb2.py
aiovemmio/gateway_pb2.pyi
aiovemmio/heartbeat.proto
aiovemmio/heartbeat_pb2.py
aiovemmio/heartbeat_pb2.pyi
aiovemmio/info.proto
aiovemmio/info_pb2.py
aiovemmio/info_pb2.pyi
aiovemmio/level.proto
aiovemmio/level_pb2.py
aiovemmio/level_pb2.pyi
aiovemmio/lock.proto
aiovemmio/lock_pb2.py
aiovemmio/lock_pb2.pyi
aiovemmio/messaging.proto
aiovemmio/messaging_pb2.py
aiovemmio/messaging_pb2.pyi
aiovemmio/metadata.proto
aiovemmio/metadata_pb2.py
aiovemmio/metadata_pb2.pyi
aiovemmio/meter.proto
aiovemmio/meter_pb2.py
aiovemmio/meter_pb2.pyi
aiovemmio/mqtt.proto
aiovemmio/mqtt_pb2.py
aiovemmio-0.5.13.dist-info/METADATA
aiovemmio-0.5.13.dist-info/WHEEL
aiovemmio-0.5.13.dist-info/RECORD
